easyorm_pkg/__init__.py
easyorm_pkg/manager.py
easyorm_pkg/test.py
easyorm_pkg/src/__init__.py
easyorm_pkg/src/config/__init__.py
easyorm_pkg/src/config/core.py
easyorm_pkg/src/modules/__init__.py
easyorm_pkg/src/modules/lunch.py
easyorm_pkg/src/packages/__init__.py
easyorm_pkg/src/packages/db_controller.py
easyorm_pkg/src/packages/db_models.py
easyorm_pkg/src/packages/db_mongo.py
easyorm_pkg/src/packages/db_mysql.py
easyorm_pkg/src/packages/db_sqlite.py
easyorm_pkg/src/packages/field.py
easyorm_pkg/src/packages/list_db_type.py
easyorm_pkg/src/server/__init__.py
easyorm_pkg/src/server/config.py
easyorm_pkg/src/server/datasource.py
easyorm_pkg/src/server/moduls.py
easyorm_pkg/src/server/server.py
easyorm-0.0.1.dist-info/LICENCE
easyorm-0.0.1.dist-info/METADATA
easyorm-0.0.1.dist-info/WHEEL
easyorm-0.0.1.dist-info/top_level.txt
easyorm-0.0.1.dist-info/RECORD
