Metadata-Version: 2.1
Name: easyorm
Version: 0.0.1
Summary: The simple basic orm to permet has execute CRUD query method
Home-page: https://github.com/Domtry/mini_orm.git
Author: Domtryr
Author-email: doffoufaye@gmail.com
License: UNKNOWN
Platform: UNKNOWN
Classifier: Programming Language :: Python :: 3
Classifier: License :: OSI Approved :: MIT License
Classifier: Operating System :: OS Independent
Requires-Python: >=3.6
